ads_pytest_parser/__init__.py
ads_pytest_parser/assoc_devops_testcase_pytest_results.py
ads_pytest_parser-0.0.2.dist-info/LICENSE
ads_pytest_parser-0.0.2.dist-info/METADATA
ads_pytest_parser-0.0.2.dist-info/WHEEL
ads_pytest_parser-0.0.2.dist-info/entry_points.txt
ads_pytest_parser-0.0.2.dist-info/top_level.txt
ads_pytest_parser-0.0.2.dist-info/RECORD
