Metadata-Version: 2.1
Name: ads-pytest-parser
Version: 0.0.2
Summary: Associate DevOps test cases with pytest XML results
Author-email: VisualLabs Kft <aron.paljakab@visuallabs.hu>, Aron Pal-Jakab <aron.paljakab@visuallabs.hu>
Project-URL: Homepage, https://github.com/VisualLabs-Kft/vl-ads-pytest-parser
Project-URL: Bug Tracker, https://github.com/VisualLabs-Kft/vl-ads-pytest-parser/issues
Classifier: Programming Language :: Python :: 3
Classifier: License :: OSI Approved :: MIT License
Classifier: Operating System :: OS Independent
Requires-Python: >=3.10
License-File: LICENSE
Requires-Dist: requests
